llm_agent_x/__init__.py
llm_agent_x/agents/__init__.py
llm_agent_x/agents/recursive_agent.py
llm_agent_x/agents/sequential_agent.py
llm_agent_x/backend/__init__.py
llm_agent_x/backend/callbacks/mermaidjs_callbacks.py
llm_agent_x/backend/config_classes/__init__.py
llm_agent_x/backend/config_classes/MergerConfig.py
llm_agent_x/backend/dot_tree.py
llm_agent_x/backend/exceptions.py
llm_agent_x/backend/get_page_text_content.py
llm_agent_x/backend/mergers/__init__.py
llm_agent_x/backend/mergers/AlgorithmicMerger.py
llm_agent_x/backend/mergers/AppendMerger.py
llm_agent_x/backend/mergers/LLMMerger.py
llm_agent_x/backend/prompt_generator.py
llm_agent_x/backend/utils.py
llm_agent_x/backend/wrappers/is_dev.py
llm_agent_x/cli.py
llm_agent_x/cli_args_parser.py
llm_agent_x/cli_evaluate.py
llm_agent_x/complexity_model.py
llm_agent_x/console.py
llm_agent_x/constants.py
llm_agent_x/llm_manager.py
llm_agent_x/main.py
llm_agent_x/tools/__init__.py
llm_agent_x/tools/brave_web_search.py
llm_agent_x/tools/exec_python.py
llm_agent_x/tools/summarize.py
llm_agent_x/tools/test_exec_python.py
llm_agent_x/tools/training_stub_tools.py
llm_agent_x/utils.py
llm_agent_x-1.0.0.dist-info/entry_points.txt
llm_agent_x-1.0.0.dist-info/LICENSE
llm_agent_x-1.0.0.dist-info/METADATA
llm_agent_x-1.0.0.dist-info/WHEEL
llm_agent_x-1.0.0.dist-info/RECORD
