Metadata-Version: 2.3
Name: llm-agent-x
Version: 1.0.0
Summary: A task execution framework using language models to perform complex tasks.
License: MIT
Author: Christopher Vaz
Author-email: christophervaz160@gmail.com
Requires-Python: >=3.9,<3.14
Classifier: License :: OSI Approved :: MIT License
Classifier: Programming Language :: Python :: 3
Classifier: Programming Language :: Python :: 3.9
Classifier: Programming Language :: Python :: 3.10
Classifier: Programming Language :: Python :: 3.11
Classifier: Programming Language :: Python :: 3.12
Classifier: Programming Language :: Python :: 3.13
Requires-Dist: arize-phoenix (>=10.5.0,<11.0.0)
Requires-Dist: astunparse (>=1.6.3,<2.0.0)
Requires-Dist: asyncio-throttle (>=1.0.2,<2.0.0)
Requires-Dist: black (>=25.1.0,<26.0.0)
Requires-Dist: bs4 (>=0.0.2,<0.0.3)
Requires-Dist: cloudpickle (>=3.1.1,<4.0.0)
Requires-Dist: huggingface-hub (>=0.32.3,<0.33.0)
Requires-Dist: icecream (>=2.1.3,<3.0.0)
Requires-Dist: langchain-community (>=0.3.24,<0.4.0)
Requires-Dist: langchain-mcp-adapters (>=0.1.7,<0.2.0) ; python_version >= "3.10" and python_version < "3.14"
Requires-Dist: langchain-openai (>=0.3.18,<0.4.0)
Requires-Dist: lxml (>=5.4.0,<6.0.0)
Requires-Dist: lxml-html-clean (>=0.4.2,<0.5.0)
Requires-Dist: mcp (>=1.9.3) ; python_version >= "3.10" and python_version < "3.14"
Requires-Dist: nest-asyncio (>=1.6.0,<2.0.0)
Requires-Dist: pydantic (>=2.0,<3.0)
Requires-Dist: pydantic-ai (>=0.2.16,<0.3.0)
Requires-Dist: pydantic-ai-slim[mcp,openai] (>=0.2.18,<0.3.0)
Requires-Dist: python-dotenv (>=1.0.0,<2.0.0)
Requires-Dist: redis (>=6.2.0,<7.0.0)
Requires-Dist: requests
Requires-Dist: rich (>=13.0.0,<14.0.0)
Requires-Dist: sentence-transformers (>=4.1.0,<5.0.0)
Requires-Dist: sumy (>=0.11.0,<0.12.0)
Requires-Dist: transformers (>=4.52.4,<5.0.0)
Requires-Dist: uvicorn (>=0.34.3,<0.35.0)
